{
  "day": 3,
  "timestamp": "2025-12-17T07:18:42.670036",
  "total_benchmarks": 4,
  "successful": 4,
  "failed": 0,
  "results": [
    {
      "benchmark_name": "FullLLMInference",
      "component": "ryot",
      "timestamp": "2025-12-17T07:18:34.638469",
      "duration_seconds": 600,
      "iterations": 5,
      "profiler_used": "py-spy",
      "min_ms": 45.3,
      "max_ms": 53.699999999999996,
      "mean_ms": 49.5,
      "median_ms": 49.5,
      "p95_ms": 53.699999999999996,
      "p99_ms": 53.699999999999996,
      "stddev_ms": 2.9698484809834986,
      "throughput": 1010.10101010101,
      "throughput_unit": "tokens/sec",
      "peak_memory_mb": 2048.0,
      "avg_memory_mb": null,
      "cpu_utilization_pct": 85.0,
      "success": true,
      "error_message": null
    },
    {
      "benchmark_name": "ScalingTest",
      "component": "all",
      "timestamp": "2025-12-17T07:18:36.645632",
      "duration_seconds": 900,
      "iterations": 3,
      "profiler_used": "py-spy",
      "min_ms": null,
      "max_ms": null,
      "mean_ms": null,
      "median_ms": null,
      "p95_ms": null,
      "p99_ms": null,
      "stddev_ms": null,
      "throughput": null,
      "throughput_unit": null,
      "peak_memory_mb": null,
      "avg_memory_mb": null,
      "cpu_utilization_pct": null,
      "success": true,
      "error_message": null
    },
    {
      "benchmark_name": "EnduranceTest",
      "component": "all",
      "timestamp": "2025-12-17T07:18:38.654879",
      "duration_seconds": 3600,
      "iterations": 1,
      "profiler_used": "memory_profiler",
      "min_ms": null,
      "max_ms": null,
      "mean_ms": null,
      "median_ms": null,
      "p95_ms": null,
      "p99_ms": null,
      "stddev_ms": null,
      "throughput": null,
      "throughput_unit": null,
      "peak_memory_mb": null,
      "avg_memory_mb": null,
      "cpu_utilization_pct": null,
      "success": true,
      "error_message": null
    },
    {
      "benchmark_name": "CollectiveWorkflow",
      "component": "all",
      "timestamp": "2025-12-17T07:18:40.665434",
      "duration_seconds": 600,
      "iterations": 5,
      "profiler_used": "py-spy",
      "min_ms": null,
      "max_ms": null,
      "mean_ms": null,
      "median_ms": null,
      "p95_ms": null,
      "p99_ms": null,
      "stddev_ms": null,
      "throughput": null,
      "throughput_unit": null,
      "peak_memory_mb": null,
      "avg_memory_mb": null,
      "cpu_utilization_pct": null,
      "success": true,
      "error_message": null
    }
  ]
}